skytemple_ssb_debugger/__init__.py
skytemple_ssb_debugger/debugger.glade
skytemple_ssb_debugger/exps.lang
skytemple_ssb_debugger/main.py
skytemple_ssb_debugger/py.typed
skytemple_ssb_debugger/ssbs.lang
skytemple_ssb_debugger/ui_util.py
skytemple_ssb_debugger/context/__init__.py
skytemple_ssb_debugger/context/abstract.py
skytemple_ssb_debugger/context/standalone.py
skytemple_ssb_debugger/controller/__init__.py
skytemple_ssb_debugger/controller/debug_overlay.py
skytemple_ssb_debugger/controller/debugger.py
skytemple_ssb_debugger/controller/editor_notebook.py
skytemple_ssb_debugger/controller/global_state.py
skytemple_ssb_debugger/controller/ground_state.py
skytemple_ssb_debugger/controller/local_variable.py
skytemple_ssb_debugger/controller/main.py
skytemple_ssb_debugger/controller/script_editor.py
skytemple_ssb_debugger/controller/ssb_editor.glade
skytemple_ssb_debugger/controller/variable.py
skytemple_ssb_debugger/controller/desmume_control_ui/PyDeSmuMe_controls.glade
skytemple_ssb_debugger/controller/desmume_control_ui/__init__.py
skytemple_ssb_debugger/controller/desmume_control_ui/joystick_controls.py
skytemple_ssb_debugger/controller/desmume_control_ui/keyboard_controls.py
skytemple_ssb_debugger/data/icons/hicolor/convert_scalable.py
skytemple_ssb_debugger/data/icons/hicolor/1024x1024/apps/skytemple-debugger.png
skytemple_ssb_debugger/data/icons/hicolor/128x128/apps/skytemple-debugger-debug-symbolic.symbolic.png
skytemple_ssb_debugger/data/icons/hicolor/128x128/apps/skytemple-debugger-disable-breaks-symbolic.symbolic.png
skytemple_ssb_debugger/data/icons/hicolor/128x128/apps/skytemple-debugger-step-into-symbolic.symbolic.png
skytemple_ssb_debugger/data/icons/hicolor/128x128/apps/skytemple-debugger-step-next-symbolic.symbolic.png
skytemple_ssb_debugger/data/icons/hicolor/128x128/apps/skytemple-debugger-step-out-symbolic.symbolic.png
skytemple_ssb_debugger/data/icons/hicolor/128x128/apps/skytemple-debugger-step-over-symbolic.symbolic.png
skytemple_ssb_debugger-1.8.2.dist-info/LICENSE
skytemple_ssb_debugger-1.8.2.dist-info/METADATA
skytemple_ssb_debugger-1.8.2.dist-info/WHEEL
skytemple_ssb_debugger-1.8.2.dist-info/entry_points.txt
skytemple_ssb_debugger-1.8.2.dist-info/top_level.txt
skytemple_ssb_debugger-1.8.2.dist-info/RECORD
