Metadata-Version: 2.1
Name: skytemple-ssb-debugger
Version: 1.8.2
Summary: Script Engine Debugger for Pokémon Mystery Dungeon Explorers of Sky
Author-email: "Marco \"Capypara\" Köpcke" <hello@capypara.de>
License: GPL-3.0-or-later
Project-URL: Homepage, https://skytemple.org
Project-URL: Announcements, https://blog.skytemple.org
Project-URL: Documentation, https://wiki.skytemple.org
Project-URL: Repository, https://github.com/SkyTemple/skytemple-ssb-debugger.git
Project-URL: Issues, https://github.com/SkyTemple/skytemple-ssb-debugger/issues
Project-URL: Discord, https://discord.gg/skytemple
Keywords: rom-hacking,game-modding,skytemple,gtk
Classifier: Development Status :: 4 - Beta
Classifier: Programming Language :: Python
Classifier: License :: OSI Approved :: GNU General Public License v3 or later (GPLv3+)
Classifier: Programming Language :: Python :: 3.9
Classifier: Programming Language :: Python :: 3.10
Classifier: Programming Language :: Python :: 3.11
Classifier: Programming Language :: Python :: 3.12
Requires-Python: >=3.9
License-File: LICENSE
Requires-Dist: ndspy >=3.0.0
Requires-Dist: skytemple-files <1.9.0,>=1.8.2
Requires-Dist: pmdsky-debug-py
Requires-Dist: skytemple-icons >=0.1.0
Requires-Dist: range-typed-integers >=1.0.0
Requires-Dist: pygobject >=3.26.0
Requires-Dist: pycairo >=1.16.0
Requires-Dist: skytemple-ssb-emulator <1.9.0,>=1.8.0
Requires-Dist: explorerscript >=0.2.1
Requires-Dist: nest-asyncio >=1.4.1
Requires-Dist: pygtkspellcheck >=5.0
Requires-Dist: importlib-metadata >=4.6 ; python_version < "3.10"
